PythonZhongwenWendang37Rumenjiaocheng/README.md
PythonZhongwenWendang37Rumenjiaocheng/__init__.py
PythonZhongwenWendang37Rumenjiaocheng/__main__.py
PythonZhongwenWendang37Rumenjiaocheng/file.epub
PythonZhongwenWendang37Rumenjiaocheng/index.html
PythonZhongwenWendang37Rumenjiaocheng/css/__init__.py
PythonZhongwenWendang37Rumenjiaocheng/css/annotations.css
PythonZhongwenWendang37Rumenjiaocheng/css/main.css
PythonZhongwenWendang37Rumenjiaocheng/css/normalize.css
PythonZhongwenWendang37Rumenjiaocheng/css/popup.css
PythonZhongwenWendang37Rumenjiaocheng/font/__init__.py
PythonZhongwenWendang37Rumenjiaocheng/font/fontello.eot
PythonZhongwenWendang37Rumenjiaocheng/font/fontello.svg
PythonZhongwenWendang37Rumenjiaocheng/font/fontello.ttf
PythonZhongwenWendang37Rumenjiaocheng/font/fontello.woff
PythonZhongwenWendang37Rumenjiaocheng/img/__init__.py
PythonZhongwenWendang37Rumenjiaocheng/img/annotator-glyph-sprite.png
PythonZhongwenWendang37Rumenjiaocheng/img/annotator-icon-sprite.png
PythonZhongwenWendang37Rumenjiaocheng/img/apple-touch-icon.png
PythonZhongwenWendang37Rumenjiaocheng/img/cancelfullscreen.png
PythonZhongwenWendang37Rumenjiaocheng/img/close.png
PythonZhongwenWendang37Rumenjiaocheng/img/fullscreen.png
PythonZhongwenWendang37Rumenjiaocheng/img/loader.gif
PythonZhongwenWendang37Rumenjiaocheng/img/menu-icon.png
PythonZhongwenWendang37Rumenjiaocheng/img/save.png
PythonZhongwenWendang37Rumenjiaocheng/img/saved.png
PythonZhongwenWendang37Rumenjiaocheng/img/settings-s.png
PythonZhongwenWendang37Rumenjiaocheng/img/settings.png
PythonZhongwenWendang37Rumenjiaocheng/img/star.png
PythonZhongwenWendang37Rumenjiaocheng/js/__init__.py
PythonZhongwenWendang37Rumenjiaocheng/js/epub.js
PythonZhongwenWendang37Rumenjiaocheng/js/epub.min.js
PythonZhongwenWendang37Rumenjiaocheng/js/epub.min.map
PythonZhongwenWendang37Rumenjiaocheng/js/hooks.min.js
PythonZhongwenWendang37Rumenjiaocheng/js/hooks.min.map
PythonZhongwenWendang37Rumenjiaocheng/js/reader.js
python_zhongwen_wendang_3_7_rumenjiaocheng-2024.3.4.0.dist-info/METADATA
python_zhongwen_wendang_3_7_rumenjiaocheng-2024.3.4.0.dist-info/WHEEL
python_zhongwen_wendang_3_7_rumenjiaocheng-2024.3.4.0.dist-info/entry_points.txt
python_zhongwen_wendang_3_7_rumenjiaocheng-2024.3.4.0.dist-info/top_level.txt
python_zhongwen_wendang_3_7_rumenjiaocheng-2024.3.4.0.dist-info/RECORD
